{
  "proof_id": "148",
  "ipfs_link": "https://ivory-advanced-sparrow-679.mypinata.cloud/ipfs/bafkreihufpucilnz5dtdsmenn5jj7i7tt3d7deivhfumbnu5qlhg3mh5me",
  "cid": "bafkreihufpucilnz5dtdsmenn5jj7i7tt3d7deivhfumbnu5qlhg3mh5me",
  "filename": "DAILY_2025-12-02.receipt.ots",
  "date": "2025-12-02",
  "time": "n/a",
  "temperature_c": "n/a",
  "weather": "n/a",
  "light_condition": "n/a",
  "notes_en": "OTS anchor file for hash validation within DGCP™ cryptographic layer.",
  "license": "MMFARM-POL-2025"
}
