{
  "proof_id": "210",
  "filename": "Proof_210_FeedRefillDuck1145.jpg",
  "date": "2025-12-05",
  "time": "11:45",
  "ipfs_link": "https://ivory-advanced-sparrow-679.mypinata.cloud/ipfs/bafybeibbzhuuvkwxwm2v2rpc3rvd7lcpchpcstxt2zknp7357yz7ijhr74",
  "cid": "bafybeibbzhuuvkwxwm2v2rpc3rvd7lcpchpcstxt2zknp7357yz7ijhr74",
  "temperature": "n/a",
  "weather": "Midday strong sunlight",
  "light_condition": "Outdoor bright light",
  "event": "Refilled duck feed",
  "layer": "Animal Welfare Evidence + Daily Farm Operation Data",
  "notes": "Ensuring remaining ducks maintain adequate nutrition under hot midday conditions.",
  "license": "MMFARM-POL-2025"
}
