{
  "dgcp_version": "DGCP-DATASET-1.0",
  "project": "MaMeeFarm",
  "framework": "DGCP",
  "record_type": "daily_proof_cid",
  "proof_id": 588,
  "date_local": "2026-02-03",
  "timezone": "Asia/Bangkok",
  "file_name": "MMFARM_DGCP_DAILY_2026-02-03_Proof588.json",
  "file_sha256": "e28a62af2c8a02b61899c2ee0df2fed70657379e3b66d77c1944dfcf3b3ed4d",
  "evidence_status": "opentimestamps_completed",
  "description": "DGCP CID record for Proof 588. OpenTimestamps verification completed. OTS reference only; primary data stored separately.",
  "activity_classification": [
    "dgcp.daily_proof",
    "cid_record",
    "integrity_timestamping",
    "ots_only_reference"
  ],
  "license": "DGCP | MMFARM-POL-2025"
}
