{
  "dgcp_version": "DGCP-DATASET-1.0",
  "project": "MaMeeFarm",
  "framework": "DGCP",
  "record_type": "daily_proof_cid",
  "proof_id": 541,
  "date_local": "2026-01-25",
  "timezone": "Asia/Bangkok",
  "file_name": "MMFARM_DGCP_DAILY_2026-01-25_Proof541.json",
  "file_sha256": "1a48bdf4dc49f97536d223d844b447ff34f62173b385d32f7d6586ed41228d4c",
  "evidence_status": "opentimestamps_completed",
  "description": "DGCP CID record for Proof 541. OpenTimestamps Stamp & Verify completed prior to repository commit.",
  "activity_classification": [
    "dgcp.daily_proof",
    "cid_record",
    "integrity_timestamping"
  ],
  "license": "DGCP | MMFARM-POL-2025"
}
